memegen/__init__.py
memegen/gui.py
memegen/tests/__init__.py
memegen/tests/conftest.py
memegen/tests/test_gui.py
memegen_desktop-0.1.1.dist-info/DESCRIPTION.rst
memegen_desktop-0.1.1.dist-info/METADATA
memegen_desktop-0.1.1.dist-info/RECORD
memegen_desktop-0.1.1.dist-info/WHEEL
memegen_desktop-0.1.1.dist-info/entry_points.txt
memegen_desktop-0.1.1.dist-info/metadata.json
memegen_desktop-0.1.1.dist-info/top_level.txt
site/__init__.py
tests/__init__.py
tests/conftest.py
tests/test_all.py
