Metadata-Version: 2.0
Name: memegen-desktop
Version: 0.1.1
Summary: Desktop client for https://memegen.link.
Home-page: https://github.com/jacebrowning/memegen-desktop
Author: Jace Browning
Author-email: jacebrowning@gmail.com
License: MIT
Platform: UNKNOWN
Classifier: Development Status :: 3 - Alpha
Classifier: Environment :: MacOS X
Classifier: Environment :: Win32 (MS Windows)
Classifier: Environment :: X11 Applications
Classifier: Intended Audience :: End Users/Desktop
Classifier: License :: OSI Approved :: MIT License
Classifier: Natural Language :: English
Classifier: Operating System :: OS Independent
Classifier: Programming Language :: Python
Classifier: Programming Language :: Python :: 3
Classifier: Programming Language :: Python :: 3.3
Classifier: Programming Language :: Python :: 3.4
Classifier: Programming Language :: Python :: 3.5
Classifier: Topic :: Games/Entertainment
Classifier: Topic :: Multimedia
Requires-Dist: Pillow (==3.3.1)
Requires-Dist: PyAudio (==0.2.9)
Requires-Dist: SpeechRecognition (==3.4.6)
Requires-Dist: pocketsphinx (==0.1.3)
Requires-Dist: requests (==2.11.1)
